django_whatsapp/__init__.py
django_whatsapp/_compat.py
django_whatsapp/apps.py
django_whatsapp/mixins.py
django_whatsapp/py.typed
django_whatsapp/utils.py
django_whatsapp/views.py
django_whatsapp-0.0.2.dist-info/METADATA
django_whatsapp-0.0.2.dist-info/WHEEL
django_whatsapp-0.0.2.dist-info/licenses/LICENSE.txt
django_whatsapp-0.0.2.dist-info/RECORD
